CHANGES.rst
DESCRIPTION.rst
LICENSE
MANIFEST.in
README.md
setup.py
src/idc/imgaug/__init__.py
src/idc/imgaug/class_lister.py
src/idc/imgaug/filter/__init__.py
src/idc/imgaug/filter/_augment_util.py
src/idc/imgaug/filter/_base_filter.py
src/idc/imgaug/filter/_base_image_augmentation.py
src/idc/imgaug/filter/_change_grayscale.py
src/idc/imgaug/filter/_clip_grayscale.py
src/idc/imgaug/filter/_crop.py
src/idc/imgaug/filter/_crop_to_label.py
src/idc/imgaug/filter/_enhance.py
src/idc/imgaug/filter/_find_contours.py
src/idc/imgaug/filter/_flip.py
src/idc/imgaug/filter/_gaussian_blur.py
src/idc/imgaug/filter/_hsl_grayscale.py
src/idc/imgaug/filter/_linear_contrast.py
src/idc/imgaug/filter/_meta_sub_images.py
src/idc/imgaug/filter/_resize.py
src/idc/imgaug/filter/_roi_images.py
src/idc/imgaug/filter/_rotate.py
src/idc/imgaug/filter/_scale.py
src/idc/imgaug/filter/_sub_images.py
src/idc/imgaug/filter/_sub_images_utils.py
src/idc/imgaug/tool/__init__.py
src/idc/imgaug/tool/combine_sub_images.py
src/idc/imgaug/tool/generate_regions.py
src/image_dataset_converter_imgaug.egg-info/PKG-INFO
src/image_dataset_converter_imgaug.egg-info/SOURCES.txt
src/image_dataset_converter_imgaug.egg-info/dependency_links.txt
src/image_dataset_converter_imgaug.egg-info/entry_points.txt
src/image_dataset_converter_imgaug.egg-info/requires.txt
src/image_dataset_converter_imgaug.egg-info/top_level.txt